MANIFEST.in
enable_drawing_pad.json
requirements.txt
setup.cfg
setup.py
jupyter_drawing_pad/__init__.py
jupyter_drawing_pad/__meta__.py
jupyter_drawing_pad/example.py
jupyter_drawing_pad/widget.py
jupyter_drawing_pad.egg-info/PKG-INFO
jupyter_drawing_pad.egg-info/SOURCES.txt
jupyter_drawing_pad.egg-info/dependency_links.txt
jupyter_drawing_pad.egg-info/not-zip-safe
jupyter_drawing_pad.egg-info/requires.txt
jupyter_drawing_pad.egg-info/top_level.txt
jupyter_drawing_pad/static/extension.js
jupyter_drawing_pad/static/index.js
jupyter_drawing_pad/static/index.js.map