Metadata-Version: 1.1
Name: jupyter-drawing-pad
Version: 0.1.3
Summary: This is a jupyter widget (or ipywidget) consisting in a drawing pad.
Home-page: https://github.com/ocoudray/jupyter-drawing-pad
Author: ocoudray
Author-email: coudray.olivier@free.fr
License: MIT
Download-URL: https://github.com/ocoudray/jupyter-drawing-pad/tarball/0.1.3
Keywords: jupyter-widget,javascript,drawing_pad
Platform: UNKNOWN
Classifier: Development Status :: 4 - Beta
Classifier: License :: OSI Approved :: MIT License
Classifier: Programming Language :: Python :: 3.5
Classifier: Programming Language :: Python :: 3.6
